tests/__init__.py
tests/test_Cell.py
tests/test_Solver.py
xl_sudoku_solver/__init__.py
xl_sudoku_solver/__main__.py
xl_sudoku_solver/cell.py
xl_sudoku_solver/exceptions.py
xl_sudoku_solver/solver.py
xl_sudoku_solver-0.0.1.post1.dist-info/DESCRIPTION.rst
xl_sudoku_solver-0.0.1.post1.dist-info/METADATA
xl_sudoku_solver-0.0.1.post1.dist-info/RECORD
xl_sudoku_solver-0.0.1.post1.dist-info/WHEEL
xl_sudoku_solver-0.0.1.post1.dist-info/entry_points.txt
xl_sudoku_solver-0.0.1.post1.dist-info/metadata.json
xl_sudoku_solver-0.0.1.post1.dist-info/top_level.txt
