Metadata-Version: 2.0
Name: xl-sudoku-solver
Version: 0.0.1.post1
Summary: A beautiful Sudoku solver
Home-page: https://github.com/lixulun/XL-Sudoku-Solver
Author: Xulun Li
Author-email: lixulun99@hotmail.com
License: MIT
Platform: UNKNOWN
